ntarp/NTarp.py
ntarp/__init__.py
ntarp/separability.py
ntarp-0.0.2.dist-info/LICENSE
ntarp-0.0.2.dist-info/METADATA
ntarp-0.0.2.dist-info/WHEEL
ntarp-0.0.2.dist-info/top_level.txt
ntarp-0.0.2.dist-info/RECORD
