Metadata-Version: 2.1
Name: ntarp
Version: 0.0.2
Summary: The NTarp clustering algorithm
Author: Alden Bradford
Project-URL: homepage, https://github.com/AldenMB/NTarp
Classifier: Programming Language :: Python :: 3
Classifier: License :: OSI Approved :: MIT License
Classifier: Operating System :: OS Independent
License-File: LICENSE
